zish/__init__.py
zish/core.py
zish-0.1.12.dist-info/METADATA
zish-0.1.12.dist-info/WHEEL
zish-0.1.12.dist-info/licenses/LICENSE
zish-0.1.12.dist-info/RECORD
